server.py
mseep_yahoo_finance_mcp-0.1.4.dist-info/licenses/LICENSE
mseep_yahoo_finance_mcp-0.1.4.dist-info/METADATA
mseep_yahoo_finance_mcp-0.1.4.dist-info/WHEEL
mseep_yahoo_finance_mcp-0.1.4.dist-info/entry_points.txt
mseep_yahoo_finance_mcp-0.1.4.dist-info/top_level.txt
mseep_yahoo_finance_mcp-0.1.4.dist-info/RECORD
